{
    "keep": {
        "days": true,
        "amount": 1
    },
    "auditLog": "C:\\Users\\shami\\Downloads\\New folder\\university-management\\logs\\winston\\errors\\.bdcfd014e92f44f83877ae5e88cc408a6311a592-audit.json",
    "files": [
        {
            "date": 1688536394149,
            "name": "C:\\Users\\shami\\Downloads\\New folder\\university-management\\logs\\winston\\errors\\UM--2023-07-05-11-ERROR.log",
            "hash": "0362a5a61c81e4f7b1bd2a19230be488f863c14d7eea4d80242c78e47d99d798"
        }
    ],
    "hashType": "sha256"
}